coslab/__init__.py
coslab/aws.py
coslab/azure_vision.py
coslab/clarify.py
coslab/common.py
coslab/coslabcli.py
coslab/googlecloud.py
coslab/tag_comparator.py
coslab/taggerresults.py
coslab_core-1.0.0.dist-info/METADATA
coslab_core-1.0.0.dist-info/WHEEL
coslab_core-1.0.0.dist-info/RECORD
