Metadata-Version: 2.4
Name: coslab-core
Version: 1.0.0
Summary: Automating social science work around image tagging via various online services.
Project-URL: Homepage, https://github.com/uh-soco/coslab-core
Project-URL: Issues, https://github.com/uh-soco/coslab-core/issues
Author-email: Matti Nelimarkka <matti.nelimarkka@helsinki.fi>, Anton Berg <anton.berg@helsinki.fi>
Classifier: License :: OSI Approved :: MIT License
Classifier: Operating System :: OS Independent
Classifier: Programming Language :: Python :: 3
Requires-Python: >=3.8
Requires-Dist: azure-cognitiveservices-vision-computervision
Requires-Dist: boto3
Requires-Dist: configparser
Requires-Dist: filetype
Requires-Dist: gensim
Requires-Dist: google-auth
Requires-Dist: google-cloud-vision
Requires-Dist: msrest
Requires-Dist: pandas
Requires-Dist: progress
Requires-Dist: progress-bar
Requires-Dist: pyyaml
Requires-Dist: scikit-learn
Requires-Dist: scipy==1.12.0
Requires-Dist: transformers
